malleus_main/__init__.py
malleus_main/cli.py
malleus_main/list_uas.py
malleus-0.0.6.dist-info/LICENSE
malleus-0.0.6.dist-info/METADATA
malleus-0.0.6.dist-info/WHEEL
malleus-0.0.6.dist-info/entry_points.txt
malleus-0.0.6.dist-info/top_level.txt
malleus-0.0.6.dist-info/RECORD
